{
	"id": "orion-belt-local-env",
	"name": "Orion Belt - Local",
	"values": [
		{
			"key": "base_url",
			"value": "http://localhost:8080",
			"type": "default",
			"enabled": true
		},
		{
			"key": "session_token",
			"value": "",
			"type": "secret",
			"enabled": true
		},
		{
			"key": "api_key",
			"value": "",
			"type": "secret",
			"enabled": true
		},
		{
			"key": "user_id",
			"value": "",
			"type": "default",
			"enabled": true
		},
		{
			"key": "machine_id",
			"value": "",
			"type": "default",
			"enabled": true
		},
		{
			"key": "access_request_id",
			"value": "",
			"type": "default",
			"enabled": true
		}
	],
	"_postman_variable_scope": "environment"
}